setup.cfg
setup.py
cliggle/__init__.py
cliggle/cli.py
cliggle/helpers.py
cliggle.egg-info/PKG-INFO
cliggle.egg-info/SOURCES.txt
cliggle.egg-info/dependency_links.txt
cliggle.egg-info/entry_points.txt
cliggle.egg-info/requires.txt
cliggle.egg-info/top_level.txt