Metadata-Version: 1.1
Name: cliggle
Version: 0.2
Summary: A CLI for Kaggle competitions.
Home-page: https://github.com/jkarimi91/cliggle
Author: Jay Karimi
Author-email: jkarimi91@gmail.com
License: MIT
Keywords: kaggle cli
Platform: Any
Classifier: License :: OSI Approved :: MIT License
Classifier: Programming Language :: Python
Classifier: Programming Language :: Python :: 2
Classifier: Programming Language :: Python :: 2.7
Classifier: Programming Language :: Python :: 3
Classifier: Programming Language :: Python :: 3.6
Classifier: Environment :: Console
Classifier: Intended Audience :: Developers
Classifier: Development Status :: 3 - Alpha
